fin_agent/__init__.py
fin_agent/backtest.py
fin_agent/config.py
fin_agent/main.py
fin_agent/notification.py
fin_agent/portfolio.py
fin_agent/scheduler.py
fin_agent/user_profile.py
fin_agent/utils.py
fin_agent/agent/__init__.py
fin_agent/agent/core.py
fin_agent/llm/__init__.py
fin_agent/llm/base.py
fin_agent/llm/deepseek_client.py
fin_agent/llm/factory.py
fin_agent/llm/openai_client.py
fin_agent/tools/__init__.py
fin_agent/tools/portfolio_tools.py
fin_agent/tools/profile_tools.py
fin_agent/tools/scheduler_tools.py
fin_agent/tools/technical_indicators.py
fin_agent/tools/tushare_tools.py
fin_agent-0.6.1.dist-info/licenses/LICENSE
fin_agent-0.6.1.dist-info/METADATA
fin_agent-0.6.1.dist-info/WHEEL
fin_agent-0.6.1.dist-info/entry_points.txt
fin_agent-0.6.1.dist-info/top_level.txt
fin_agent-0.6.1.dist-info/RECORD
